{"25810398": {"best_seller": {}, "genre": ""}, "25666046": {"best_seller": {"E-Book Fiction": [{"date": "Jan 07, 2017", "rank": 5, "weeks": 1}], "Combined Print & E-Book Fiction": [{"date": "Jan 07, 2017", "rank": 15, "weeks": 1}]}, "genre": "Fiction"}, "30555488": {"best_seller": {"Hardcover Fiction": [{"date": "Jan 07, 2017", "rank": 5, "weeks": 22}], "Combined Print & E-Book Fiction": [{"date": "Jan 07, 2017", "rank": 11, "weeks": 13}]}, "genre": "Fiction"}, "25489025": {"best_seller": {}, "genre": ""}, "30078108": {"best_seller": {}, "genre": ""}, "25658482": {"best_seller": {}, "genre": ""}, "27833494": {"best_seller": {"Paperback Nonfiction": [{"date": "Apr 01, 2017", "rank": 7, "weeks": 6}, {"date": "Mar 25, 2017", "rank": 4, "weeks": 5}, {"date": "Feb 25, 2017", "rank": 8, "weeks": 4}, {"date": "Feb 11, 2017", "rank": 9, "weeks": 3}, {"date": "Feb 04, 2017", "rank": 5, "weeks": 2}, {"date": "Jan 28, 2017", "rank": 4, "weeks": 1}], "E-Book Nonfiction": [{"date": "Dec 31, 2016", "rank": 6, "weeks": 4}], "Combined Print & E-Book Nonfiction": [{"date": "Mar 26, 2016", "rank": 10, "weeks": 10}, {"date": "Mar 19, 2016", "rank": 3, "weeks": 9}], "Hardcover Nonfiction": [{"date": "Mar 19, 2016", "rank": 2, "weeks": 9}], "Politics and American History": [{"date": "Mar 26, 2016", "rank": 1, "weeks": 0}]}, "genre": "Nonfiction"}, "25852784": {"best_seller": {"Paperback Nonfiction": [{"date": "May 27, 2017", "rank": 8, "weeks": 7}, {"date": "May 13, 2017", "rank": 10, "weeks": 6}, {"date": "May 06, 2017", "rank": 6, "weeks": 5}, {"date": "Apr 29, 2017", "rank": 10, "weeks": 4}, {"date": "Apr 15, 2017", "rank": 9, "weeks": 3}, {"date": "Mar 18, 2017", "rank": 10, "weeks": 2}, {"date": "Mar 04, 2017", "rank": 7, "weeks": 1}], "E-Book Nonfiction": [{"date": "Mar 05, 2016", "rank": 10, "weeks": 1}], "Combined Print & E-Book Nonfiction": [{"date": "Mar 05, 2016", "rank": 7, "weeks": 1}], "Politics and American History": [{"date": "Mar 26, 2016", "rank": 4, "weeks": 0}], "Hardcover Nonfiction": [{"date": "Mar 05, 2016", "rank": 6, "weeks": 1}]}, "genre": "Nonfiction"}, "29370484": {"best_seller": {}, "genre": ""}, "28007895": {"best_seller": {}, "genre": ""}, "497499": {"best_seller": {}, "genre": ""}, "22929586": {"best_seller": {"Hardcover Fiction": [{"date": "Aug 29, 2015", "rank": 15, "weeks": 1}, {"date": "Aug 22, 2015", "rank": 18, "weeks": 0}]}, "genre": "Fiction"}, "21400742": {"best_seller": {}, "genre": ""}, "22237161": {"best_seller": {"Paperback Trade Fiction": [{"date": "Oct 29, 2016", "rank": 3, "weeks": 1}], "Combined Print & E-Book Fiction": [{"date": "Nov 05, 2016", "rank": 17, "weeks": 0}, {"date": "Oct 29, 2016", "rank": 11, "weeks": 1}], "E-Book Fiction": [{"date": "Oct 29, 2016", "rank": 9, "weeks": 1}]}, "genre": "Fiction"}, "25242224": {"best_seller": {"Paperback Trade Fiction": [{"date": "Dec 19, 2015", "rank": 15, "weeks": 0}, {"date": "Oct 03, 2015", "rank": 15, "weeks": 0}, {"date": "Sep 26, 2015", "rank": 10, "weeks": 4}, {"date": "Sep 19, 2015", "rank": 10, "weeks": 3}, {"date": "Sep 12, 2015", "rank": 7, "weeks": 2}, {"date": "Sep 05, 2015", "rank": 3, "weeks": 1}]}, "genre": "Fiction"}, "25489625": {"best_seller": {"Hardcover Nonfiction": [{"date": "Nov 05, 2016", "rank": 19, "weeks": 0}], "Combined Print & E-Book Nonfiction": [{"date": "Nov 12, 2016", "rank": 20, "weeks": 0}], "Race and Civil Rights": [{"date": "Oct 29, 2016", "rank": 1, "weeks": 0}], "Politics and American History": [{"date": "Oct 29, 2016", "rank": 4, "weeks": 0}]}, "genre": "Nonfiction"}, "20758057": {"best_seller": {"Fashion, Manners and Customs": [{"date": "Feb 28, 2015", "rank": 5, "weeks": 0}], "Race and Civil Rights": [{"date": "Mar 28, 2015", "rank": 15, "weeks": 0}], "Business": [{"date": "Jan 02, 2016", "rank": 10, "weeks": 0}]}, "genre": ""}, "18803640": {"best_seller": {}, "genre": ""}, "23995249": {"best_seller": {"Science": [{"date": "Sep 26, 2015", "rank": 18, "weeks": 0}], "Expeditions": [{"date": "Sep 26, 2015", "rank": 5, "weeks": 0}], "Hardcover Nonfiction": [{"date": "Oct 03, 2015", "rank": 19, "weeks": 0}]}, "genre": "Nonfiction"}, "22237163": {"best_seller": {"Crime and Punishment": [{"date": "Dec 26, 2015", "rank": 10, "weeks": 0}]}, "genre": ""}, "18143977": {"best_seller": {"Paperback Trade Fiction": [{"date": "Apr 08, 2017", "rank": 4, "weeks": 1}], "Combined Print & E-Book Fiction": [{"date": "Apr 15, 2017", "rank": 13, "weeks": 80}, {"date": "Apr 08, 2017", "rank": 11, "weeks": 79}], "Hardcover Fiction": [{"date": "Jan 14, 2017", "rank": 20, "weeks": 0}, {"date": "Jan 07, 2017", "rank": 19, "weeks": 0}, {"date": "Dec 31, 2016", "rank": 16, "weeks": 134}, {"date": "Dec 24, 2016", "rank": 10, "weeks": 133}]}, "genre": "Fiction"}, "17402288": {"best_seller": {}, "genre": ""}, "18467802": {"best_seller": {}, "genre": ""}, "22253764": {"best_seller": {}, "genre": ""}, "18114068": {"best_seller": {"Paperback Trade Fiction": [{"date": "Mar 21, 2015", "rank": 18, "weeks": 0}, {"date": "Mar 14, 2015", "rank": 12, "weeks": 0}, {"date": "Mar 07, 2015", "rank": 13, "weeks": 0}, {"date": "Feb 28, 2015", "rank": 8, "weeks": 1}], "Hardcover Fiction": [{"date": "Dec 13, 2014", "rank": 19, "weeks": 0}, {"date": "Dec 06, 2014", "rank": 18, "weeks": 0}, {"date": "Nov 29, 2014", "rank": 19, "weeks": 0}, {"date": "Mar 15, 2014", "rank": 14, "weeks": 1}, {"date": "Mar 08, 2014", "rank": 20, "weeks": 0}], "Combined Print & E-Book Fiction": [{"date": "Dec 20, 2014", "rank": 15, "weeks": 1}]}, "genre": "Fiction"}, "18594409": {"best_seller": {"Hardcover Graphic Books": [{"date": "Jun 04, 2016", "rank": 10, "weeks": 100}, {"date": "May 28, 2016", "rank": 8, "weeks": 99}, {"date": "Apr 09, 2016", "rank": 6, "weeks": 98}, {"date": "Apr 02, 2016", "rank": 7, "weeks": 97}, {"date": "Mar 12, 2016", "rank": 6, "weeks": 96}, {"date": "Mar 05, 2016", "rank": 9, "weeks": 95}, {"date": "Feb 20, 2016", "rank": 5, "weeks": 94}, {"date": "Feb 13, 2016", "rank": 6, "weeks": 93}, {"date": "Feb 06, 2016", "rank": 4, "weeks": 92}, {"date": "Jan 30, 2016", "rank": 4, "weeks": 91}, {"date": "Jan 23, 2016", "rank": 8, "weeks": 90}, {"date": "Jan 16, 2016", "rank": 5, "weeks": 89}, {"date": "Jan 09, 2016", "rank": 2, "weeks": 88}, {"date": "Jan 02, 2016", "rank": 7, "weeks": 87}, {"date": "Dec 26, 2015", "rank": 6, "weeks": 86}, {"date": "Dec 19, 2015", "rank": 6, "weeks": 85}, {"date": "Dec 12, 2015", "rank": 6, "weeks": 84}, {"date": "Dec 05, 2015", "rank": 6, "weeks": 83}, {"date": "Nov 28, 2015", "rank": 7, "weeks": 82}, {"date": "Nov 21, 2015", "rank": 7, "weeks": 81}]}, "genre": ""}, "20613511": {"best_seller": {"Health": [{"date": "Dec 27, 2014", "rank": 5, "weeks": 0}, {"date": "Oct 25, 2014", "rank": 7, "weeks": 0}]}, "genre": ""}, "17612573": {"best_seller": {}, "genre": ""}, "17910054": {"best_seller": {"Science": [{"date": "Apr 25, 2015", "rank": 12, "weeks": 0}, {"date": "Mar 28, 2015", "rank": 17, "weeks": 0}, {"date": "Feb 28, 2015", "rank": 13, "weeks": 0}], "Paperback Nonfiction": [{"date": "Feb 21, 2015", "rank": 15, "weeks": 0}, {"date": "Feb 14, 2015", "rank": 17, "weeks": 0}, {"date": "Feb 07, 2015", "rank": 14, "weeks": 0}]}, "genre": "Nonfiction"}, "21965079": {"best_seller": {"Hardcover Nonfiction": [{"date": "Sep 20, 2014", "rank": 11, "weeks": 1}]}, "genre": "Nonfiction"}, "15796700": {"best_seller": {"Paperback Trade Fiction": [{"date": "Sep 05, 2015", "rank": 15, "weeks": 0}, {"date": "Aug 29, 2015", "rank": 13, "weeks": 0}, {"date": "Aug 15, 2015", "rank": 14, "weeks": 0}, {"date": "Aug 08, 2015", "rank": 17, "weeks": 0}, {"date": "Aug 01, 2015", "rank": 18, "weeks": 0}, {"date": "Jul 25, 2015", "rank": 19, "weeks": 0}, {"date": "Jul 18, 2015", "rank": 16, "weeks": 0}, {"date": "Jul 11, 2015", "rank": 16, "weeks": 0}, {"date": "Jul 04, 2015", "rank": 16, "weeks": 0}, {"date": "Jun 27, 2015", "rank": 17, "weeks": 0}, {"date": "Jun 20, 2015", "rank": 18, "weeks": 0}, {"date": "Jun 13, 2015", "rank": 15, "weeks": 0}, {"date": "Jun 06, 2015", "rank": 16, "weeks": 0}, {"date": "May 30, 2015", "rank": 15, "weeks": 0}, {"date": "May 23, 2015", "rank": 17, "weeks": 0}, {"date": "May 16, 2015", "rank": 14, "weeks": 0}, {"date": "May 09, 2015", "rank": 17, "weeks": 0}, {"date": "May 02, 2015", "rank": 15, "weeks": 0}, {"date": "Apr 25, 2015", "rank": 16, "weeks": 0}, {"date": "Apr 11, 2015", "rank": 18, "weeks": 0}]}, "genre": "Fiction"}, "15803141": {"best_seller": {"Paperback Trade Fiction": [{"date": "Mar 08, 2014", "rank": 25, "weeks": 0}, {"date": "Mar 01, 2014", "rank": 18, "weeks": 5}, {"date": "Feb 22, 2014", "rank": 18, "weeks": 4}, {"date": "Feb 15, 2014", "rank": 20, "weeks": 3}, {"date": "Feb 08, 2014", "rank": 19, "weeks": 2}, {"date": "Jan 18, 2014", "rank": 14, "weeks": 1}], "Hardcover Fiction": [{"date": "Apr 20, 2013", "rank": 31, "weeks": 0}]}, "genre": "Fiction"}, "17333223": {"best_seller": {"Paperback Trade Fiction": [{"date": "Jan 02, 2016", "rank": 15, "weeks": 0}, {"date": "Dec 26, 2015", "rank": 15, "weeks": 0}, {"date": "Dec 19, 2015", "rank": 12, "weeks": 0}, {"date": "Dec 12, 2015", "rank": 14, "weeks": 0}, {"date": "Dec 05, 2015", "rank": 13, "weeks": 0}, {"date": "Oct 03, 2015", "rank": 14, "weeks": 0}, {"date": "Sep 26, 2015", "rank": 13, "weeks": 0}, {"date": "Sep 19, 2015", "rank": 15, "weeks": 0}, {"date": "Sep 12, 2015", "rank": 9, "weeks": 22}, {"date": "Sep 05, 2015", "rank": 11, "weeks": 0}, {"date": "Aug 29, 2015", "rank": 9, "weeks": 21}, {"date": "Aug 22, 2015", "rank": 9, "weeks": 20}, {"date": "Aug 15, 2015", "rank": 9, "weeks": 19}, {"date": "Aug 08, 2015", "rank": 9, "weeks": 18}, {"date": "Aug 01, 2015", "rank": 8, "weeks": 17}, {"date": "Jul 25, 2015", "rank": 10, "weeks": 16}, {"date": "Jul 18, 2015", "rank": 5, "weeks": 15}, {"date": "Jul 11, 2015", "rank": 7, "weeks": 14}, {"date": "Jul 04, 2015", "rank": 5, "weeks": 13}, {"date": "Jun 27, 2015", "rank": 4, "weeks": 12}]}, "genre": "Fiction"}, "15790842": {"best_seller": {"Paperback Trade Fiction": [{"date": "Apr 12, 2014", "rank": 17, "weeks": 14}, {"date": "Apr 05, 2014", "rank": 20, "weeks": 13}, {"date": "Mar 29, 2014", "rank": 15, "weeks": 12}, {"date": "Mar 22, 2014", "rank": 13, "weeks": 11}, {"date": "Mar 15, 2014", "rank": 9, "weeks": 10}, {"date": "Mar 08, 2014", "rank": 3, "weeks": 9}, {"date": "Mar 01, 2014", "rank": 3, "weeks": 8}, {"date": "Feb 22, 2014", "rank": 4, "weeks": 7}, {"date": "Feb 15, 2014", "rank": 6, "weeks": 6}, {"date": "Feb 08, 2014", "rank": 3, "weeks": 5}, {"date": "Feb 01, 2014", "rank": 2, "weeks": 4}, {"date": "Jan 25, 2014", "rank": 1, "weeks": 3}, {"date": "Jan 18, 2014", "rank": 1, "weeks": 2}, {"date": "Jan 11, 2014", "rank": 1, "weeks": 1}], "Hardcover Fiction": [{"date": "Jan 04, 2014", "rank": 22, "weeks": 0}, {"date": "Aug 03, 2013", "rank": 25, "weeks": 0}, {"date": "Jul 06, 2013", "rank": 19, "weeks": 0}, {"date": "Jun 01, 2013", "rank": 14, "weeks": 8}, {"date": "May 25, 2013", "rank": 13, "weeks": 7}, {"date": "May 18, 2013", "rank": 17, "weeks": 0}]}, "genre": "Fiction"}, "13641208": {"best_seller": {"Paperback Trade Fiction": [{"date": "Feb 15, 2014", "rank": 22, "weeks": 0}, {"date": "Feb 08, 2014", "rank": 13, "weeks": 5}, {"date": "Feb 01, 2014", "rank": 12, "weeks": 4}, {"date": "Jan 25, 2014", "rank": 13, "weeks": 3}, {"date": "Jan 18, 2014", "rank": 8, "weeks": 2}, {"date": "Jan 11, 2014", "rank": 5, "weeks": 1}], "Hardcover Fiction": [{"date": "Feb 23, 2013", "rank": 6, "weeks": 7}, {"date": "Feb 16, 2013", "rank": 3, "weeks": 6}], "Combined Hardcover & Paperback Fiction": [{"date": "Mar 02, 2013", "rank": 27, "weeks": 0}, {"date": "Feb 23, 2013", "rank": 13, "weeks": 0}], "Combined Print & E-Book Fiction": [{"date": "Feb 16, 2013", "rank": 18, "weeks": 0}]}, "genre": "Fiction"}, "15811560": {"best_seller": {"Hardcover Nonfiction": [{"date": "Feb 09, 2013", "rank": 27, "weeks": 0}, {"date": "Jan 26, 2013", "rank": 30, "weeks": 0}]}, "genre": "Nonfiction"}, "17288658": {"best_seller": {"E-Book Nonfiction": [{"date": "Oct 26, 2013", "rank": 18, "weeks": 1}], "Combined Print & E-Book Nonfiction": [{"date": "Oct 26, 2013", "rank": 20, "weeks": 0}], "Hardcover Nonfiction": [{"date": "Oct 26, 2013", "rank": 19, "weeks": 0}]}, "genre": "Nonfiction"}, "17704902": {"best_seller": {"Science": [{"date": "Sep 28, 2013", "rank": 1, "weeks": 0}], "E-Book Nonfiction": [{"date": "Sep 21, 2013", "rank": 10, "weeks": 2}, {"date": "Sep 14, 2013", "rank": 6, "weeks": 1}], "Combined Print & E-Book Nonfiction": [{"date": "Sep 14, 2013", "rank": 8, "weeks": 1}], "Hardcover Nonfiction": [{"date": "Sep 14, 2013", "rank": 11, "weeks": 1}], "Politics and American History": [{"date": "Sep 28, 2013", "rank": 6, "weeks": 0}]}, "genre": "Nonfiction"}, "18669169": {"best_seller": {"E-Book Nonfiction": [{"date": "Mar 26, 2016", "rank": 5, "weeks": 1}], "Combined Print & E-Book Nonfiction": [{"date": "May 18, 2013", "rank": 25, "weeks": 0}], "Paperback Nonfiction": [{"date": "Apr 12, 2014", "rank": 25, "weeks": 0}, {"date": "Mar 22, 2014", "rank": 17, "weeks": 1}], "Hardcover Nonfiction": [{"date": "Mar 30, 2013", "rank": 30, "weeks": 0}, {"date": "Mar 23, 2013", "rank": 28, "weeks": 0}]}, "genre": "Nonfiction"}, "15771862": {"best_seller": {"Hardcover Nonfiction": [{"date": "Mar 09, 2013", "rank": 29, "weeks": 0}], "E-Book Nonfiction": [{"date": "Mar 09, 2013", "rank": 15, "weeks": 1}], "Combined Hardcover & Paperback Nonfiction": [{"date": "Mar 30, 2013", "rank": 34, "weeks": 0}], "Combined Print & E-Book Nonfiction": [{"date": "Mar 09, 2013", "rank": 18, "weeks": 0}]}, "genre": "Nonfiction"}, "13507212": {"best_seller": {"Paperback Trade Fiction": [{"date": "Apr 11, 2015", "rank": 19, "weeks": 0}, {"date": "Jun 01, 2013", "rank": 16, "weeks": 4}, {"date": "May 25, 2013", "rank": 15, "weeks": 3}, {"date": "May 18, 2013", "rank": 12, "weeks": 2}, {"date": "May 11, 2013", "rank": 4, "weeks": 1}], "Hardcover Fiction": [{"date": "Dec 08, 2012", "rank": 25, "weeks": 0}, {"date": "Dec 01, 2012", "rank": 24, "weeks": 0}, {"date": "Nov 24, 2012", "rank": 33, "weeks": 0}, {"date": "Nov 03, 2012", "rank": 31, "weeks": 0}, {"date": "Oct 27, 2012", "rank": 22, "weeks": 0}, {"date": "Oct 20, 2012", "rank": 22, "weeks": 0}, {"date": "Aug 04, 2012", "rank": 30, "weeks": 0}, {"date": "Jul 28, 2012", "rank": 31, "weeks": 0}], "Combined Hardcover & Paperback Fiction": [{"date": "Dec 15, 2012", "rank": 23, "weeks": 0}]}, "genre": "Fiction"}, "13573235": {"best_seller": {"Hardcover Graphic Books": [{"date": "Sep 14, 2013", "rank": 10, "weeks": 27}, {"date": "Aug 31, 2013", "rank": 7, "weeks": 26}, {"date": "Apr 20, 2013", "rank": 3, "weeks": 25}, {"date": "Mar 23, 2013", "rank": 10, "weeks": 24}, {"date": "Mar 09, 2013", "rank": 10, "weeks": 23}, {"date": "Mar 02, 2013", "rank": 7, "weeks": 22}, {"date": "Feb 23, 2013", "rank": 9, "weeks": 21}, {"date": "Feb 16, 2013", "rank": 8, "weeks": 20}, {"date": "Feb 09, 2013", "rank": 2, "weeks": 19}, {"date": "Feb 02, 2013", "rank": 1, "weeks": 18}, {"date": "Jan 26, 2013", "rank": 1, "weeks": 17}, {"date": "Jan 19, 2013", "rank": 1, "weeks": 16}, {"date": "Jan 12, 2013", "rank": 1, "weeks": 15}, {"date": "Jan 05, 2013", "rank": 1, "weeks": 14}, {"date": "Dec 29, 2012", "rank": 1, "weeks": 13}, {"date": "Dec 22, 2012", "rank": 1, "weeks": 12}, {"date": "Dec 15, 2012", "rank": 3, "weeks": 11}, {"date": "Dec 08, 2012", "rank": 2, "weeks": 10}, {"date": "Dec 01, 2012", "rank": 2, "weeks": 9}, {"date": "Nov 24, 2012", "rank": 2, "weeks": 8}]}, "genre": ""}, "13722902": {"best_seller": {"Paperback Trade Fiction": [{"date": "Jul 13, 2013", "rank": 24, "weeks": 0}, {"date": "Jul 06, 2013", "rank": 23, "weeks": 0}, {"date": "Jun 29, 2013", "rank": 25, "weeks": 0}, {"date": "Jun 22, 2013", "rank": 20, "weeks": 2}, {"date": "Jun 15, 2013", "rank": 19, "weeks": 1}], "Hardcover Fiction": [{"date": "Dec 22, 2012", "rank": 34, "weeks": 0}, {"date": "Aug 04, 2012", "rank": 25, "weeks": 0}, {"date": "Jul 28, 2012", "rank": 16, "weeks": 0}, {"date": "Jul 21, 2012", "rank": 27, "weeks": 0}, {"date": "Jul 14, 2012", "rank": 32, "weeks": 0}, {"date": "Jul 07, 2012", "rank": 27, "weeks": 0}, {"date": "Jun 30, 2012", "rank": 31, "weeks": 0}, {"date": "Jun 23, 2012", "rank": 16, "weeks": 1}]}, "genre": "Fiction"}, "13537891": {"best_seller": {}, "genre": ""}, "13366259": {"best_seller": {"Paperback Trade Fiction": [{"date": "May 25, 2013", "rank": 23, "weeks": 0}, {"date": "May 18, 2013", "rank": 21, "weeks": 0}, {"date": "May 11, 2013", "rank": 23, "weeks": 0}, {"date": "May 04, 2013", "rank": 18, "weeks": 1}], "Hardcover Fiction": [{"date": "Oct 13, 2012", "rank": 26, "weeks": 0}, {"date": "Sep 29, 2012", "rank": 31, "weeks": 0}, {"date": "Sep 22, 2012", "rank": 24, "weeks": 0}], "Combined Hardcover & Paperback Fiction": [{"date": "Oct 27, 2012", "rank": 30, "weeks": 0}]}, "genre": "Fiction"}, "11869272": {"best_seller": {"Paperback Nonfiction": [{"date": "May 17, 2014", "rank": 4, "weeks": 6}], "Combined Print & E-Book Nonfiction": [{"date": "May 24, 2014", "rank": 18, "weeks": 0}], "Politics and American History": [{"date": "May 24, 2014", "rank": 8, "weeks": 0}]}, "genre": "Nonfiction"}, "13547504": {"best_seller": {"Science": [{"date": "Mar 29, 2014", "rank": 14, "weeks": 0}], "Paperback Nonfiction": [{"date": "Mar 22, 2014", "rank": 24, "weeks": 0}, {"date": "Oct 26, 2013", "rank": 10, "weeks": 4}, {"date": "Oct 19, 2013", "rank": 13, "weeks": 3}, {"date": "Oct 12, 2013", "rank": 14, "weeks": 2}, {"date": "Oct 05, 2013", "rank": 13, "weeks": 1}], "E-Book Nonfiction": [{"date": "Dec 29, 2012", "rank": 35, "weeks": 0}], "Hardcover Nonfiction": [{"date": "Dec 29, 2012", "rank": 19, "weeks": 0}], "Combined Hardcover & Paperback Nonfiction": [{"date": "Dec 29, 2012", "rank": 23, "weeks": 0}], "Combined Print & E-Book Nonfiction": [{"date": "Jan 05, 2013", "rank": 32, "weeks": 0}]}, "genre": "Nonfiction"}, "13049569": {"best_seller": {"Paperback Nonfiction": [{"date": "May 18, 2013", "rank": 22, "weeks": 0}], "Hardcover Nonfiction": [{"date": "Jun 16, 2012", "rank": 11, "weeks": 7}], "Combined Hardcover & Paperback Nonfiction": [{"date": "Jun 23, 2012", "rank": 27, "weeks": 0}], "Politics and American History": [{"date": "Jun 23, 2012", "rank": 7, "weeks": 0}], "Combined Print & E-Book Nonfiction": [{"date": "Jun 16, 2012", "rank": 14, "weeks": 7}], "E-Book Nonfiction": [{"date": "Jun 16, 2012", "rank": 33, "weeks": 0}]}, "genre": "Nonfiction"}, "13588421": {"best_seller": {"Politics and American History": [{"date": "Dec 29, 2012", "rank": 9, "weeks": 0}], "Hardcover Nonfiction": [{"date": "Dec 01, 2012", "rank": 16, "weeks": 0}], "Combined Hardcover & Paperback Nonfiction": [{"date": "Dec 01, 2012", "rank": 20, "weeks": 0}], "Combined Print & E-Book Nonfiction": [{"date": "Dec 01, 2012", "rank": 22, "weeks": 0}], "E-Book Nonfiction": [{"date": "Nov 24, 2012", "rank": 17, "weeks": 1}]}, "genre": "Nonfiction"}, "8854815": {"best_seller": {"Paperback Nonfiction": [{"date": "Apr 27, 2013", "rank": 24, "weeks": 0}, {"date": "Apr 20, 2013", "rank": 18, "weeks": 2}, {"date": "Apr 13, 2013", "rank": 27, "weeks": 0}, {"date": "Apr 06, 2013", "rank": 17, "weeks": 1}], "Hardcover Nonfiction": [{"date": "Aug 04, 2012", "rank": 13, "weeks": 1}], "Combined Hardcover & Paperback Nonfiction": [{"date": "Aug 04, 2012", "rank": 22, "weeks": 0}], "E-Book Nonfiction": [{"date": "Dec 15, 2012", "rank": 24, "weeks": 1}, {"date": "Dec 08, 2012", "rank": 33, "weeks": 0}], "Combined Print & E-Book Nonfiction": [{"date": "Aug 04, 2012", "rank": 28, "weeks": 0}]}, "genre": "Nonfiction"}, "10996342": {"best_seller": {"Combined Print & E-Book Fiction": [{"date": "Jan 05, 2013", "rank": 31, "weeks": 0}], "E-Book Fiction": [{"date": "Jan 05, 2013", "rank": 30, "weeks": 0}], "Paperback Trade Fiction": [{"date": "Sep 15, 2012", "rank": 34, "weeks": 0}, {"date": "Sep 08, 2012", "rank": 32, "weeks": 0}, {"date": "Sep 01, 2012", "rank": 26, "weeks": 0}, {"date": "Aug 25, 2012", "rank": 27, "weeks": 0}, {"date": "Aug 18, 2012", "rank": 21, "weeks": 0}, {"date": "Aug 11, 2012", "rank": 18, "weeks": 15}, {"date": "Aug 04, 2012", "rank": 19, "weeks": 14}, {"date": "Jul 28, 2012", "rank": 16, "weeks": 13}, {"date": "Jul 21, 2012", "rank": 16, "weeks": 12}, {"date": "Jul 14, 2012", "rank": 18, "weeks": 11}, {"date": "Jul 07, 2012", "rank": 17, "weeks": 10}, {"date": "Jun 30, 2012", "rank": 17, "weeks": 9}, {"date": "Jun 23, 2012", "rank": 16, "weeks": 8}, {"date": "Jun 16, 2012", "rank": 12, "weeks": 7}, {"date": "Jun 09, 2012", "rank": 14, "weeks": 6}, {"date": "Jun 02, 2012", "rank": 14, "weeks": 5}, {"date": "May 26, 2012", "rank": 7, "weeks": 4}], "Combined Hardcover & Paperback Fiction": [{"date": "May 26, 2012", "rank": 24, "weeks": 0}]}, "genre": "Fiction"}, "10644930": {"best_seller": {"Paperback Mass-Market Fiction": [{"date": "Feb 13, 2016", "rank": 5, "weeks": 3}, {"date": "Feb 06, 2016", "rank": 6, "weeks": 2}, {"date": "Jan 30, 2016", "rank": 10, "weeks": 1}], "Combined Print & E-Book Fiction": [{"date": "Feb 20, 2016", "rank": 15, "weeks": 19}], "Paperback Trade Fiction": [{"date": "Dec 21, 2013", "rank": 19, "weeks": 18}, {"date": "Dec 14, 2013", "rank": 16, "weeks": 17}, {"date": "Dec 07, 2013", "rank": 16, "weeks": 16}, {"date": "Nov 30, 2013", "rank": 21, "weeks": 0}, {"date": "Nov 23, 2013", "rank": 24, "weeks": 0}], "E-Book Fiction": [{"date": "Nov 23, 2013", "rank": 4, "weeks": 24}]}, "genre": "Fiction"}, "8584686": {"best_seller": {"Hardcover Fiction": [{"date": "Feb 12, 2011", "rank": 12, "weeks": 1}, {"date": "Feb 05, 2011", "rank": 28, "weeks": 0}], "Combined Hardcover & Paperback Fiction": [{"date": "Feb 19, 2011", "rank": 35, "weeks": 0}, {"date": "Feb 12, 2011", "rank": 35, "weeks": 0}]}, "genre": "Fiction"}, "9680533": {"best_seller": {}, "genre": ""}, "8366402": {"best_seller": {"Paperback Trade Fiction": [{"date": "Mar 30, 2013", "rank": 31, "weeks": 0}, {"date": "Mar 23, 2013", "rank": 18, "weeks": 35}, {"date": "Dec 15, 2012", "rank": 31, "weeks": 0}, {"date": "Dec 08, 2012", "rank": 29, "weeks": 0}, {"date": "Dec 01, 2012", "rank": 32, "weeks": 0}, {"date": "Nov 24, 2012", "rank": 24, "weeks": 0}, {"date": "Sep 29, 2012", "rank": 30, "weeks": 0}, {"date": "Sep 22, 2012", "rank": 26, "weeks": 0}, {"date": "Sep 15, 2012", "rank": 26, "weeks": 0}, {"date": "Sep 08, 2012", "rank": 35, "weeks": 0}, {"date": "Sep 01, 2012", "rank": 27, "weeks": 0}, {"date": "Aug 25, 2012", "rank": 17, "weeks": 34}, {"date": "Aug 18, 2012", "rank": 34, "weeks": 0}, {"date": "Aug 11, 2012", "rank": 32, "weeks": 0}, {"date": "Aug 04, 2012", "rank": 32, "weeks": 0}, {"date": "Jul 28, 2012", "rank": 20, "weeks": 33}, {"date": "Jul 21, 2012", "rank": 19, "weeks": 32}, {"date": "Jul 14, 2012", "rank": 23, "weeks": 0}, {"date": "Jul 07, 2012", "rank": 19, "weeks": 31}, {"date": "Jun 30, 2012", "rank": 16, "weeks": 30}]}, "genre": "Fiction"}, "10383597": {"best_seller": {}, "genre": ""}, "9809455": {"best_seller": {}, "genre": ""}, "7940589": {"best_seller": {"Hardcover Nonfiction": [{"date": "Apr 09, 2011", "rank": 3, "weeks": 1}], "Combined Hardcover & Paperback Nonfiction": [{"date": "Apr 09, 2011", "rank": 5, "weeks": 0}], "Combined Print & E-Book Nonfiction": [{"date": "Apr 09, 2011", "rank": 6, "weeks": 1}], "E-Book Nonfiction": [{"date": "Apr 09, 2011", "rank": 7, "weeks": 1}]}, "genre": "Nonfiction"}, "11468377": {"best_seller": {"Business": [{"date": "Feb 25, 2017", "rank": 5, "weeks": 0}], "Science": [{"date": "Feb 25, 2017", "rank": 7, "weeks": 0}], "Paperback Nonfiction": [{"date": "Feb 18, 2017", "rank": 6, "weeks": 124}, {"date": "Feb 11, 2017", "rank": 7, "weeks": 123}, {"date": "Feb 04, 2017", "rank": 7, "weeks": 122}]}, "genre": "Nonfiction"}, "8796854": {"best_seller": {"Combined Print & E-Book Nonfiction": [{"date": "Jul 12, 2014", "rank": 11, "weeks": 1}], "E-Book Nonfiction": [{"date": "Jul 12, 2014", "rank": 6, "weeks": 1}], "Politics and American History": [{"date": "Jul 30, 2011", "rank": 10, "weeks": 0}], "Hardcover Nonfiction": [{"date": "Jul 02, 2011", "rank": 24, "weeks": 0}], "Combined Hardcover & Paperback Nonfiction": [{"date": "Jul 09, 2011", "rank": 31, "weeks": 0}]}, "genre": "Nonfiction"}, "7905092": {"best_seller": {"Paperback Trade Fiction": [{"date": "Oct 01, 2011", "rank": 7, "weeks": 1}], "Combined Hardcover & Paperback Fiction": [{"date": "Oct 08, 2011", "rank": 24, "weeks": 0}], "Hardcover Fiction": [{"date": "Jun 04, 2011", "rank": 31, "weeks": 0}, {"date": "Mar 19, 2011", "rank": 31, "weeks": 0}, {"date": "Mar 12, 2011", "rank": 32, "weeks": 0}, {"date": "Mar 05, 2011", "rank": 34, "weeks": 0}, {"date": "Feb 26, 2011", "rank": 32, "weeks": 0}, {"date": "Feb 19, 2011", "rank": 26, "weeks": 0}, {"date": "Feb 12, 2011", "rank": 25, "weeks": 0}], "E-Book Fiction": [{"date": "Feb 12, 2011", "rank": 31, "weeks": 0}]}, "genre": "Fiction"}, "7841455": {"best_seller": {}, "genre": ""}, "7937843": {"best_seller": {"Paperback Trade Fiction": [{"date": "Feb 20, 2016", "rank": 10, "weeks": 45}, {"date": "Feb 13, 2016", "rank": 11, "weeks": 0}, {"date": "Feb 06, 2016", "rank": 10, "weeks": 44}, {"date": "Jan 30, 2016", "rank": 9, "weeks": 43}, {"date": "Jan 23, 2016", "rank": 7, "weeks": 42}, {"date": "Jan 16, 2016", "rank": 7, "weeks": 41}], "Combined Print & E-Book Fiction": [{"date": "Feb 27, 2016", "rank": 19, "weeks": 0}], "E-Book Fiction": [{"date": "Mar 05, 2016", "rank": 8, "weeks": 11}]}, "genre": "Fiction"}, "8701280": {"best_seller": {}, "genre": ""}, "7331435": {"best_seller": {"Paperback Trade Fiction": [{"date": "Apr 21, 2012", "rank": 31, "weeks": 0}, {"date": "Mar 31, 2012", "rank": 22, "weeks": 0}, {"date": "Mar 10, 2012", "rank": 34, "weeks": 0}, {"date": "Mar 03, 2012", "rank": 30, "weeks": 0}, {"date": "Feb 25, 2012", "rank": 28, "weeks": 0}, {"date": "Feb 18, 2012", "rank": 25, "weeks": 0}, {"date": "Feb 11, 2012", "rank": 22, "weeks": 0}, {"date": "Feb 04, 2012", "rank": 20, "weeks": 46}, {"date": "Jan 28, 2012", "rank": 18, "weeks": 45}, {"date": "Jan 21, 2012", "rank": 18, "weeks": 44}, {"date": "Jan 14, 2012", "rank": 18, "weeks": 43}, {"date": "Jan 07, 2012", "rank": 17, "weeks": 42}, {"date": "Dec 31, 2011", "rank": 20, "weeks": 41}, {"date": "Dec 24, 2011", "rank": 18, "weeks": 40}, {"date": "Dec 17, 2011", "rank": 14, "weeks": 39}, {"date": "Dec 10, 2011", "rank": 20, "weeks": 38}, {"date": "Dec 03, 2011", "rank": 17, "weeks": 37}, {"date": "Nov 26, 2011", "rank": 19, "weeks": 36}, {"date": "Nov 19, 2011", "rank": 17, "weeks": 35}, {"date": "Nov 12, 2011", "rank": 18, "weeks": 34}]}, "genre": "Fiction"}, "8268599": {"best_seller": {"Hardcover Nonfiction": [{"date": "Jan 16, 2011", "rank": 29, "weeks": 0}, {"date": "Jan 09, 2011", "rank": 29, "weeks": 0}, {"date": "Jan 02, 2011", "rank": 30, "weeks": 0}, {"date": "Dec 26, 2010", "rank": 34, "weeks": 0}, {"date": "Dec 19, 2010", "rank": 18, "weeks": 0}, {"date": "Dec 05, 2010", "rank": 31, "weeks": 0}]}, "genre": "Nonfiction"}, "7968243": {"best_seller": {"Paperback Nonfiction": [{"date": "Nov 12, 2011", "rank": 6, "weeks": 10}], "Combined Hardcover & Paperback Nonfiction": [{"date": "Nov 05, 2011", "rank": 28, "weeks": 0}], "Combined Print & E-Book Nonfiction": [{"date": "Nov 12, 2011", "rank": 30, "weeks": 0}]}, "genre": "Nonfiction"}, "7170627": {"best_seller": {"Paperback Nonfiction": [{"date": "Feb 09, 2013", "rank": 29, "weeks": 0}, {"date": "Jul 28, 2012", "rank": 31, "weeks": 0}, {"date": "Jul 14, 2012", "rank": 26, "weeks": 0}, {"date": "Jul 07, 2012", "rank": 32, "weeks": 0}], "Science": [{"date": "Mar 28, 2015", "rank": 20, "weeks": 0}], "Health": [{"date": "Nov 29, 2014", "rank": 9, "weeks": 0}], "Combined Print & E-Book Nonfiction": [{"date": "Apr 04, 2015", "rank": 15, "weeks": 3}], "E-Book Nonfiction": [{"date": "Apr 04, 2015", "rank": 20, "weeks": 0}]}, "genre": "Nonfiction"}, "7769406": {"best_seller": {"Hardcover Nonfiction": [{"date": "Jan 09, 2011", "rank": 35, "weeks": 0}, {"date": "Jan 02, 2011", "rank": 31, "weeks": 0}, {"date": "Dec 19, 2010", "rank": 23, "weeks": 0}, {"date": "Dec 12, 2010", "rank": 31, "weeks": 0}, {"date": "Dec 05, 2010", "rank": 30, "weeks": 0}, {"date": "Nov 28, 2010", "rank": 29, "weeks": 0}, {"date": "Nov 21, 2010", "rank": 30, "weeks": 0}, {"date": "Nov 14, 2010", "rank": 26, "weeks": 0}, {"date": "Nov 07, 2010", "rank": 18, "weeks": 0}, {"date": "Oct 31, 2010", "rank": 11, "weeks": 1}]}, "genre": "Nonfiction"}, "8171378": {"best_seller": {"Race and Civil Rights": [{"date": "May 28, 2016", "rank": 9, "weeks": 0}, {"date": "Dec 26, 2015", "rank": 9, "weeks": 0}, {"date": "Aug 29, 2015", "rank": 10, "weeks": 0}, {"date": "Jul 25, 2015", "rank": 12, "weeks": 0}, {"date": "Jun 27, 2015", "rank": 12, "weeks": 0}, {"date": "Dec 27, 2014", "rank": 8, "weeks": 0}, {"date": "Nov 29, 2014", "rank": 13, "weeks": 0}], "Paperback Nonfiction": [{"date": "Mar 02, 2013", "rank": 34, "weeks": 0}, {"date": "Jan 26, 2013", "rank": 27, "weeks": 0}, {"date": "Jul 07, 2012", "rank": 31, "weeks": 0}, {"date": "May 12, 2012", "rank": 33, "weeks": 0}, {"date": "May 05, 2012", "rank": 25, "weeks": 0}, {"date": "Apr 28, 2012", "rank": 26, "weeks": 0}, {"date": "Apr 21, 2012", "rank": 32, "weeks": 0}, {"date": "Apr 14, 2012", "rank": 35, "weeks": 0}, {"date": "Apr 07, 2012", "rank": 20, "weeks": 24}, {"date": "Mar 31, 2012", "rank": 20, "weeks": 23}, {"date": "Mar 17, 2012", "rank": 20, "weeks": 22}]}, "genre": "Nonfiction"}, "5948644": {"best_seller": {}, "genre": ""}, "6085191": {"best_seller": {}, "genre": ""}, "6076387": {"best_seller": {}, "genre": ""}, "6366437": {"best_seller": {"Paperback Trade Fiction": [{"date": "Oct 01, 2011", "rank": 31, "weeks": 0}, {"date": "Sep 24, 2011", "rank": 29, "weeks": 0}, {"date": "Sep 17, 2011", "rank": 29, "weeks": 0}, {"date": "Sep 10, 2011", "rank": 32, "weeks": 0}, {"date": "Aug 13, 2011", "rank": 30, "weeks": 0}, {"date": "Jul 30, 2011", "rank": 34, "weeks": 0}, {"date": "Jun 18, 2011", "rank": 33, "weeks": 0}, {"date": "Jun 04, 2011", "rank": 33, "weeks": 0}, {"date": "May 21, 2011", "rank": 31, "weeks": 0}, {"date": "May 07, 2011", "rank": 28, "weeks": 0}, {"date": "Apr 30, 2011", "rank": 34, "weeks": 0}, {"date": "Apr 23, 2011", "rank": 31, "weeks": 0}, {"date": "Apr 16, 2011", "rank": 29, "weeks": 0}, {"date": "Apr 09, 2011", "rank": 30, "weeks": 0}, {"date": "Apr 02, 2011", "rank": 24, "weeks": 0}, {"date": "Mar 26, 2011", "rank": 20, "weeks": 29}, {"date": "Mar 19, 2011", "rank": 21, "weeks": 0}, {"date": "Mar 12, 2011", "rank": 18, "weeks": 27}, {"date": "Mar 05, 2011", "rank": 16, "weeks": 26}, {"date": "Feb 26, 2011", "rank": 18, "weeks": 25}]}, "genre": "Fiction"}, "3863987": {"best_seller": {}, "genre": ""}, "4371507": {"best_seller": {}, "genre": ""}, "6633912": {"best_seller": {"Paperback Nonfiction": [{"date": "Nov 14, 2010", "rank": 34, "weeks": 0}, {"date": "Nov 07, 2010", "rank": 33, "weeks": 0}, {"date": "Oct 24, 2010", "rank": 34, "weeks": 0}, {"date": "Oct 10, 2010", "rank": 32, "weeks": 0}, {"date": "Oct 03, 2010", "rank": 20, "weeks": 4}, {"date": "Sep 26, 2010", "rank": 26, "weeks": 0}, {"date": "Sep 19, 2010", "rank": 25, "weeks": 0}, {"date": "Sep 12, 2010", "rank": 20, "weeks": 3}, {"date": "Sep 05, 2010", "rank": 32, "weeks": 0}, {"date": "Aug 29, 2010", "rank": 12, "weeks": 2}, {"date": "Aug 22, 2010", "rank": 22, "weeks": 0}, {"date": "Aug 15, 2010", "rank": 14, "weeks": 1}, {"date": "Aug 08, 2010", "rank": 27, "weeks": 0}], "Hardcover Nonfiction": [{"date": "Jan 03, 2010", "rank": 33, "weeks": 0}, {"date": "Oct 24, 2009", "rank": 32, "weeks": 0}, {"date": "Oct 17, 2009", "rank": 18, "weeks": 0}, {"date": "Oct 10, 2009", "rank": 35, "weeks": 0}]}, "genre": "Nonfiction"}, "6340016": {"best_seller": {"Paperback Nonfiction": [{"date": "Nov 28, 2010", "rank": 21, "weeks": 0}, {"date": "Nov 14, 2010", "rank": 35, "weeks": 0}, {"date": "Oct 24, 2010", "rank": 35, "weeks": 0}, {"date": "Oct 10, 2010", "rank": 31, "weeks": 0}, {"date": "Oct 03, 2010", "rank": 32, "weeks": 0}, {"date": "Sep 26, 2010", "rank": 28, "weeks": 0}, {"date": "Sep 19, 2010", "rank": 33, "weeks": 0}, {"date": "Sep 12, 2010", "rank": 26, "weeks": 0}, {"date": "Sep 05, 2010", "rank": 20, "weeks": 10}, {"date": "Aug 29, 2010", "rank": 15, "weeks": 9}, {"date": "Aug 22, 2010", "rank": 14, "weeks": 8}, {"date": "Aug 15, 2010", "rank": 13, "weeks": 7}, {"date": "Aug 08, 2010", "rank": 16, "weeks": 6}, {"date": "Aug 01, 2010", "rank": 14, "weeks": 5}, {"date": "Jul 25, 2010", "rank": 6, "weeks": 4}, {"date": "Jul 18, 2010", "rank": 10, "weeks": 3}, {"date": "Jul 11, 2010", "rank": 14, "weeks": 2}, {"date": "Jul 04, 2010", "rank": 8, "weeks": 1}], "Hardcover Nonfiction": [{"date": "Jan 24, 2010", "rank": 35, "weeks": 0}, {"date": "Jan 17, 2010", "rank": 30, "weeks": 0}]}, "genre": "Nonfiction"}, "6025160": {"best_seller": {}, "genre": ""}, "5789689": {"best_seller": {}, "genre": ""}, "1540810": {"best_seller": {}, "genre": ""}, "3009435": {"best_seller": {}, "genre": ""}, "2615008": {"best_seller": {}, "genre": ""}, "63032": {"best_seller": {}, "genre": ""}, "85301": {"best_seller": {}, "genre": ""}, "3280003": {"best_seller": {}, "genre": ""}, "2517439": {"best_seller": {}, "genre": ""}, "2982466": {"best_seller": {}, "genre": ""}, "1283566": {"best_seller": {}, "genre": ""}, "3006513": {"best_seller": {}, "genre": ""}, "79420": {"best_seller": {}, "genre": ""}, "398323": {"best_seller": {}, "genre": ""}, "63033": {"best_seller": {}, "genre": ""}, "97782": {"best_seller": {}, "genre": ""}, "271074": {"best_seller": {}, "genre": ""}, "22121": {"best_seller": {}, "genre": ""}, "771858": {"best_seller": {}, "genre": ""}, "280410": {"best_seller": {}, "genre": ""}, "382787": {"best_seller": {}, "genre": ""}, "392563": {"best_seller": {}, "genre": ""}, "70509": {"best_seller": {}, "genre": ""}, "33299": {"best_seller": {}, "genre": ""}, "3648": {"best_seller": {}, "genre": ""}, "12372": {"best_seller": {}, "genre": ""}, "3483": {"best_seller": {}, "genre": ""}, "76339": {"best_seller": {}, "genre": ""}, "110890": {"best_seller": {}, "genre": ""}, "4820": {"best_seller": {}, "genre": ""}, "3109": {"best_seller": {}, "genre": ""}, "95643": {"best_seller": {}, "genre": ""}, "4929": {"best_seller": {}, "genre": ""}, "3679": {"best_seller": {}, "genre": ""}, "9844": {"best_seller": {}, "genre": ""}, "5015": {"best_seller": {}, "genre": ""}, "22259": {"best_seller": {}, "genre": ""}, "87119": {"best_seller": {}, "genre": ""}, "2557": {"best_seller": {}, "genre": ""}, "27398": {"best_seller": {"Combined Print & E-Book Nonfiction": [{"date": "Apr 30, 2016", "rank": 18, "weeks": 0}], "Culture": [{"date": "Apr 30, 2016", "rank": 10, "weeks": 0}], "E-Book Nonfiction": [{"date": "Apr 30, 2016", "rank": 4, "weeks": 1}]}, "genre": "Nonfiction"}, "29658": {"best_seller": {}, "genre": ""}, "7815": {"best_seller": {}, "genre": ""}, "68210": {"best_seller": {}, "genre": ""}, "43691": {"best_seller": {}, "genre": ""}, "703": {"best_seller": {}, "genre": ""}, "14280": {"best_seller": {}, "genre": ""}, "11691": {"best_seller": {}, "genre": ""}, "14729": {"best_seller": {}, "genre": ""}, "16130": {"best_seller": {"Paperback Nonfiction": [{"date": "Jan 28, 2017", "rank": 2, "weeks": 68}], "Combined Print & E-Book Nonfiction": [{"date": "Feb 04, 2017", "rank": 8, "weeks": 58}, {"date": "Jan 28, 2017", "rank": 7, "weeks": 57}]}, "genre": "Nonfiction"}, "14318": {"best_seller": {}, "genre": ""}, "1206073": {"best_seller": {}, "genre": ""}, "5129": {"best_seller": {}, "genre": ""}, "335795": {"best_seller": {}, "genre": ""}, "18723": {"best_seller": {}, "genre": ""}, "24724": {"best_seller": {}, "genre": ""}, "9799": {"best_seller": {}, "genre": ""}, "334050": {"best_seller": {}, "genre": ""}, "67": {"best_seller": {}, "genre": ""}, "4392": {"best_seller": {}, "genre": ""}, "385255": {"best_seller": {}, "genre": ""}, "333295": {"best_seller": {}, "genre": ""}, "833266": {"best_seller": {}, "genre": ""}, "6867": {"best_seller": {"Paperback Trade Fiction": [{"date": "Jun 07, 2008", "rank": 32, "weeks": 0}]}, "genre": "Fiction"}, "179684": {"best_seller": {}, "genre": ""}, "2187": {"best_seller": {}, "genre": ""}, "26348": {"best_seller": {}, "genre": ""}, "765047": {"best_seller": {}, "genre": ""}, "310328": {"best_seller": {}, "genre": ""}, "88442": {"best_seller": {}, "genre": ""}, "172050": {"best_seller": {}, "genre": ""}, "3805": {"best_seller": {}, "genre": ""}, "111126": {"best_seller": {"Paperback Trade Fiction": [{"date": "Oct 26, 2013", "rank": 16, "weeks": 1}]}, "genre": "Fiction"}, "2203": {"best_seller": {}, "genre": ""}, "16276": {"best_seller": {}, "genre": ""}, "28202": {"best_seller": {}, "genre": ""}, "110090": {"best_seller": {}, "genre": ""}, "64664": {"best_seller": {}, "genre": ""}, "92559": {"best_seller": {}, "genre": ""}, "52357": {"best_seller": {}, "genre": ""}, "4591": {"best_seller": {}, "genre": ""}, "98160": {"best_seller": {}, "genre": ""}, "4953": {"best_seller": {"Parenthood and Family": [{"date": "Oct 25, 2014", "rank": 4, "weeks": 0}], "E-Book Nonfiction": [{"date": "Oct 18, 2014", "rank": 17, "weeks": 0}]}, "genre": "Nonfiction"}, "11734": {"best_seller": {}, "genre": ""}, "57545": {"best_seller": {}, "genre": ""}, "148190": {"best_seller": {}, "genre": ""}, "310844": {"best_seller": {}, "genre": ""}, "3711": {"best_seller": {}, "genre": ""}, "726514": {"best_seller": {}, "genre": ""}, "27999": {"best_seller": {}, "genre": ""}, "451464": {"best_seller": {}, "genre": ""}, "6192": {"best_seller": {}, "genre": ""}, "125777": {"best_seller": {}, "genre": ""}, "8914": {"best_seller": {}, "genre": ""}, "132245": {"best_seller": {}, "genre": ""}, "1325761": {"best_seller": {}, "genre": ""}, "48840": {"best_seller": {}, "genre": ""}, "89840": {"best_seller": {}, "genre": ""}, "42718": {"best_seller": {}, "genre": ""}, "19631": {"best_seller": {}, "genre": ""}, "26931": {"best_seller": {}, "genre": ""}, "373571": {"best_seller": {}, "genre": ""}, "111151": {"best_seller": {}, "genre": ""}, "7244": {"best_seller": {"Combined Print & E-Book Fiction": [{"date": "Jan 12, 2013", "rank": 29, "weeks": 0}], "E-Book Fiction": [{"date": "Jan 12, 2013", "rank": 21, "weeks": 1}]}, "genre": "Fiction"}, "1040401": {"best_seller": {}, "genre": ""}, "16121": {"best_seller": {}, "genre": ""}, "455632": {"best_seller": {}, "genre": ""}, "224953": {"best_seller": {}, "genre": ""}, "63043": {"best_seller": {}, "genre": ""}, "11472": {"best_seller": {}, "genre": ""}, "11650": {"best_seller": {}, "genre": ""}, "200836": {"best_seller": {}, "genre": ""}, "11728": {"best_seller": {}, "genre": ""}, "255021": {"best_seller": {}, "genre": ""}, "1898": {"best_seller": {"Expeditions": [{"date": "Sep 26, 2015", "rank": 4, "weeks": 0}, {"date": "Jul 25, 2015", "rank": 12, "weeks": 0}], "E-Book Nonfiction": [{"date": "Oct 03, 2015", "rank": 15, "weeks": 0}, {"date": "Sep 26, 2015", "rank": 10, "weeks": 1}]}, "genre": "Nonfiction"}, "413": {"best_seller": {}, "genre": ""}, "162950": {"best_seller": {}, "genre": ""}, "205054": {"best_seller": {}, "genre": ""}, "11761": {"best_seller": {}, "genre": ""}, "18846": {"best_seller": {}, "genre": ""}, "310330": {"best_seller": {}, "genre": ""}, "493323": {"best_seller": {}, "genre": ""}, "252577": {"best_seller": {}, "genre": ""}, "497183": {"best_seller": {}, "genre": ""}, "398586": {"best_seller": {}, "genre": ""}, "391221": {"best_seller": {}, "genre": ""}, "9865": {"best_seller": {}, "genre": ""}, "14281": {"best_seller": {"Paperback Trade Fiction": [{"date": "Oct 26, 2013", "rank": 21, "weeks": 0}]}, "genre": "Fiction"}, "546725": {"best_seller": {}, "genre": ""}, "25622782": {"best_seller": {}, "genre": ""}, "30688435": {"best_seller": {"Hardcover Fiction": [{"date": "Apr 01, 2017", "rank": 13, "weeks": 4}, {"date": "Mar 25, 2017", "rank": 13, "weeks": 3}, {"date": "Mar 18, 2017", "rank": 9, "weeks": 2}, {"date": "Mar 11, 2017", "rank": 5, "weeks": 1}]}, "genre": "Fiction"}, "29983711": {"best_seller": {"Paperback Trade Fiction": [{"date": "Dec 16, 2017", "rank": 10, "weeks": 2}, {"date": "Dec 09, 2017", "rank": 10, "weeks": 1}]}, "genre": "Fiction"}, "28446947":{"best_seller": {}, "genre": ""}, "29751398": {"best_seller": {}, "genre": ""}, "32920226": {"best_seller": {"Hardcover Fiction": [{"date": "Sep 30, 2017", "rank": 15, "weeks": 1}]}, "genre": "Fiction"}, "31624963": {"best_seller": {}, "genre": ""}, "34237826": {"best_seller": {"Hardcover Nonfiction": [{"date": "Nov 04, 2017", "rank": 5, "weeks": 4}], "Combined Print & E-Book Nonfiction": [{"date": "Nov 04, 2017", "rank": 5, "weeks": 4}, {"date": "Oct 28, 2017", "rank": 5, "weeks": 3}]}, "genre": "Nonfiction"}, "34846249": {"best_seller": {}, "genre": ""}, "33911349": {"best_seller": {}, "genre": ""}, "31920820": {"best_seller": {}, "genre": ""}, "35297339": {"best_seller": {}, "genre": ""}, "36739329": {"best_seller": {}, "genre": ""}, "38330854": {"best_seller": {}, "genre": ""}, "36692478": {"best_seller": {"Hardcover Fiction": [{"date": "Jun 30, 2018", "rank": 8, "weeks": 4}, {"date": "Jun 23, 2018", "rank": 8, "weeks": 3}, {"date": "Jun 16, 2018", "rank": 12, "weeks": 2}, {"date": "Jun 09, 2018", "rank": 13, "weeks": 1}], "Combined Print & E-Book Fiction": [{"date": "Jul 07, 2018", "rank": 15, "weeks": 1}]}, "genre": "Fiction"}, "38140077": {"best_seller": {}, "genre": ""}, "38561954": {"best_seller": {}, "genre": ""}, "35133922": {"best_seller": {"Hardcover Nonfiction": [{"date": "Sep 29, 2018", "rank": 6, "weeks": 32}], "Combined Print & E-Book Nonfiction": [{"date": "Sep 29, 2018", "rank": 4, "weeks": 32}], "Audio Nonfiction": [{"date": "Sep 29, 2018", "rank": 3, "weeks": 0}]}, "genre": "Nonfiction"}, "38530663": {"best_seller": {}, "genre": ""}, "36613747": {"best_seller": {}, "genre": ""}, "39218044": {"best_seller": {"Hardcover Nonfiction": [{"date": "Sep 15, 2018", "rank": 14, "weeks": 2}, {"date": "Sep 08, 2018", "rank": 6, "weeks": 1}], "Combined Print & E-Book Nonfiction": [{"date": "Sep 08, 2018", "rank": 4, "weeks": 1}]}, "genre": "Nonfiction"}, "34563821": {"best_seller": {}, "genre": ""}, "43565369": {"best_seller": {}, "genre": ""}, "41160292": {"best_seller": {"Hardcover Fiction": [{"date": "May 25, 2019", "rank": 15, "weeks": 3}, {"date": "May 18, 2019", "rank": 15, "weeks": 2}, {"date": "May 11, 2019", "rank": 15, "weeks": 1}]}, "genre": "Fiction"}, "40245130": {"best_seller": {}, "genre": ""}, "43256597": {"best_seller": {}, "genre": ""}, "40163119": {"best_seller": {}, "genre": ""}, "41154986": {"best_seller": {}, "genre": ""}, "43347603": {"best_seller": {}, "genre": ""}, "33786693": {"best_seller": {}, "genre": ""}, "40538681": {"best_seller": {"Audio Nonfiction": [{"date": "Jun 29, 2019", "rank": 9, "weeks": 0}], "Combined Print & E-Book Nonfiction": [{"date": "Feb 16, 2019", "rank": 12, "weeks": 1}]}, "genre": "Nonfiction"},"53122391": {"best_seller": {}, "genre": ""}, "51045613": {"best_seller": {"Hardcover Fiction": [{"date": "Jun 20, 2020", "rank": 7, "weeks": 3}, {"date": "Mar 14, 2020", "rank": 15, "weeks": 2}, {"date": "Mar 07, 2020", "rank": 14, "weeks": 1}], "Combined Print & E-Book Fiction": [{"date": "Jun 20, 2020", "rank": 11, "weeks": 1}]}, "genre": "Fiction"}, "43890641": {"best_seller": {}, "genre": ""}, "50358133": {"best_seller": {}, "genre": ""}, "51791252": {"best_seller": {}, "genre": ""}, "50088631": {"best_seller": {"Audio Nonfiction": [{"date": "May 02, 2020", "rank": 8, "weeks": 0}], "Hardcover Nonfiction": [{"date": "Apr 18, 2020", "rank": 5, "weeks": 2}, {"date": "Apr 11, 2020", "rank": 4, "weeks": 1}], "Combined Print & E-Book Nonfiction": [{"date": "Apr 11, 2020", "rank": 1, "weeks": 1}]}, "genre": "Nonfiction"}, "55361205": {"best_seller": {"Hardcover Nonfiction": [{"date": "Nov 21, 2020", "rank": 1, "weeks": 1}], "Combined Print & E-Book Nonfiction": [{"date": "Nov 21, 2020", "rank": 1, "weeks": 1}]}, "genre": "Nonfiction"}, "49512631": {"best_seller": {}, "genre": ""}, "45186565": {"best_seller": {}, "genre": ""}, "17345257": {"best_seller": {}, "genre": ""}, "51794532": {"best_seller": {}, "genre": ""}, "55918474": {"best_seller": {}, "genre": ""}, "51183428": {"best_seller": {"Hardcover Fiction": [{"date": "Sep 04, 2021", "rank": 12, "weeks": 2}, {"date": "Aug 28, 2021", "rank": 4, "weeks": 1}], "Combined Print & E-Book Fiction": [{"date": "Aug 28, 2021", "rank": 10, "weeks": 1}]}, "genre": "Fiction"}, "53733106": {"best_seller": {}, "genre": ""}, "62069739": {"best_seller": {}, "genre": ""}, "53317528": {"best_seller": {}, "genre": ""}, "156935444": {"best_seller": {}, "genre": ""}, "57359691": {"best_seller": {}, "genre": ""}, "55298325": {"best_seller": {}, "genre": ""}, "48721389": {"best_seller": {}, "genre": ""}, "58437521": {"best_seller": {}, "genre": ""}, "58386758": {"best_seller": {}, "genre": ""}, "60194162": {"best_seller": {}, "genre": ""}, "59900679": {"best_seller": {}, "genre": ""}, "58210933": {"best_seller": {}, "genre": ""}, "59575939": {"best_seller": {}, "genre": ""}, "60429621": {"best_seller": {}, "genre": ""}, "59808605": {"best_seller": {}, "genre": ""}, "59148724": {"best_seller": {}, "genre": ""}, "56769525": {"best_seller": {}, "genre": ""}}